[
    {
        "corp_code": "00110750",
        "corp_name": "플루토스",
        "stock_code": "019570",
        "corp_cls": "K",
        "report_nm": "[기재정정]주주총회소집공고",
        "rcept_no": "20260512000734",
        "flr_nm": "플루토스",
        "rcept_dt": "20260512",
        "rm": "정"
    },
    {
        "corp_code": "00872656",
        "corp_name": "금양그린파워",
        "stock_code": "282720",
        "corp_cls": "K",
        "report_nm": "주주총회소집공고",
        "rcept_no": "20260512000652",
        "flr_nm": "금양그린파워",
        "rcept_dt": "20260512",
        "rm": ""
    },
    {
        "corp_code": "01307335",
        "corp_name": "공구우먼",
        "stock_code": "366030",
        "corp_cls": "K",
        "report_nm": "[기재정정]주주총회소집공고",
        "rcept_no": "20260512000641",
        "flr_nm": "공구우먼",
        "rcept_dt": "20260512",
        "rm": "정"
    },
    {
        "corp_code": "00372873",
        "corp_name": "KTis",
        "stock_code": "058860",
        "corp_cls": "Y",
        "report_nm": "주주총회소집공고",
        "rcept_no": "20260512000613",
        "flr_nm": "KTis",
        "rcept_dt": "20260512",
        "rm": ""
    },
    {
        "corp_code": "00351427",
        "corp_name": "와이즈넛",
        "stock_code": "096250",
        "corp_cls": "K",
        "report_nm": "주주총회소집공고",
        "rcept_no": "20260512000585",
        "flr_nm": "와이즈넛",
        "rcept_dt": "20260512",
        "rm": ""
    },
    {
        "corp_code": "00370200",
        "corp_name": "아이로보틱스",
        "stock_code": "066430",
        "corp_cls": "K",
        "report_nm": "[기재정정]주주총회소집공고",
        "rcept_no": "20260512000582",
        "flr_nm": "아이로보틱스",
        "rcept_dt": "20260512",
        "rm": "정"
    },
    {
        "corp_code": "00370200",
        "corp_name": "아이로보틱스",
        "stock_code": "066430",
        "corp_cls": "K",
        "report_nm": "[기재정정]주주총회소집공고",
        "rcept_no": "20260512000518",
        "flr_nm": "아이로보틱스",
        "rcept_dt": "20260512",
        "rm": "정"
    },
    {
        "corp_code": "00372882",
        "corp_name": "KTcs",
        "stock_code": "058850",
        "corp_cls": "Y",
        "report_nm": "주주총회소집공고",
        "rcept_no": "20260512000376",
        "flr_nm": "KTcs",
        "rcept_dt": "20260512",
        "rm": ""
    },
    {
        "corp_code": "01050738",
        "corp_name": "솔트룩스",
        "stock_code": "304100",
        "corp_cls": "K",
        "report_nm": "[기재정정]주주총회소집공고",
        "rcept_no": "20260512000021",
        "flr_nm": "솔트룩스",
        "rcept_dt": "20260512",
        "rm": ""
    }
]